LICENSE
MANIFEST.in
README.rst
VERSION
setup.cfg
setup.py
twopi_flask_utils/__init__.py
twopi_flask_utils.egg-info/PKG-INFO
twopi_flask_utils.egg-info/SOURCES.txt
twopi_flask_utils.egg-info/dependency_links.txt
twopi_flask_utils.egg-info/not-zip-safe
twopi_flask_utils.egg-info/requires.txt
twopi_flask_utils.egg-info/top_level.txt
twopi_flask_utils/celery/__init__.py
twopi_flask_utils/config/__init__.py
twopi_flask_utils/deployment_release/__init__.py
twopi_flask_utils/pagination/__init__.py
twopi_flask_utils/restful/__init__.py
twopi_flask_utils/sentry/__init__.py
twopi_flask_utils/testing/__init__.py
twopi_flask_utils/token_auth/ShortlivedTokenMixin.py
twopi_flask_utils/token_auth/__init__.py
twopi_flask_utils/token_auth/decorators.py
twopi_flask_utils/webargs/__init__.py