Metadata-Version: 1.0
Name: twopi-flask-utils
Version: 1.1.8
Summary: A set of utilities to make working with flask web applications easier.
Home-page: https://github.com/TwoPiCode/twopi-flask-utils
Author: Nick Whyte
Author-email: nick@twopicode.com
License: UNKNOWN
Platform: UNKNOWN
